begs.py
begs-0.1.9.dist-info/LICENSE
begs-0.1.9.dist-info/METADATA
begs-0.1.9.dist-info/WHEEL
begs-0.1.9.dist-info/top_level.txt
begs-0.1.9.dist-info/RECORD
