Metadata-Version: 2.1
Name: begs
Version: 0.1.9
Summary: A rewrite of the famous requests library with better defaults and certificate handling
Home-page: https://github.com/grintor/begs
Author: Chris Wheeler
Author-email: grintor@gmail.com
License: MIT
Platform: UNKNOWN
Classifier: License :: OSI Approved :: MIT License
Classifier: Programming Language :: Python :: 3
Classifier: Programming Language :: Python :: 3.7
Classifier: Programming Language :: Python :: 3.8
Classifier: Programming Language :: Python :: 3.9
Classifier: Programming Language :: Python :: 3.10
Classifier: Programming Language :: Python :: 3.11
License-File: LICENSE
